LICENSE
MANIFEST.in
README.rst
setup.py
bin/opqpwdcliclient
django_opqpwd.egg-info/PKG-INFO
django_opqpwd.egg-info/SOURCES.txt
django_opqpwd.egg-info/dependency_links.txt
django_opqpwd.egg-info/requires.txt
django_opqpwd.egg-info/top_level.txt
opqpwd/__init__.py
opqpwd/admin.py
opqpwd/apps.py
opqpwd/authentication.py
opqpwd/clientfun.py
opqpwd/cryptofun.py
opqpwd/models.py
opqpwd/permissions.py
opqpwd/serializers.py
opqpwd/tests.py
opqpwd/urls.py
opqpwd/views.py
opqpwd/migrations/0001_initial.py
opqpwd/migrations/0002_auto_20161105_1600.py
opqpwd/migrations/0003_auto_20161105_1707.py
opqpwd/migrations/0004_auto_20161108_1242.py
opqpwd/migrations/0005_auto_20161111_1400.py
opqpwd/migrations/0006_auto_20161111_1400.py
opqpwd/migrations/0007_auto_20161115_1445.py
opqpwd/migrations/0008_auto_20161115_1630.py
opqpwd/migrations/0009_auto_20161115_1659.py
opqpwd/migrations/0010_auto_20161115_1806.py
opqpwd/migrations/__init__.py