Metadata-Version: 1.1
Name: django-opqpwd
Version: 0.1
Summary: A Django-based password manager REST service with client-side encryption
Home-page: https://github.com/marcobellaccini/django-opqpwd
Author: Marco Bellaccini
Author-email: marco.bellaccini[at!]gmail.com
License: Apache License 2.0
Platform: UNKNOWN
Classifier: Environment :: Web Environment
Classifier: Framework :: Django
Classifier: Framework :: Django :: 1.10
Classifier: Intended Audience :: Developers
Classifier: License :: OSI Approved :: Apache Software License
Classifier: Operating System :: OS Independent
Classifier: Programming Language :: Python
Classifier: Programming Language :: Python :: 3
Classifier: Programming Language :: Python :: 3.4
Classifier: Programming Language :: Python :: 3.5
Classifier: Topic :: Internet :: WWW/HTTP
Classifier: Topic :: Internet :: WWW/HTTP :: Dynamic Content
